spider_brew_kit/__init__.py
spider_brew_kit/contants.py
spider_brew_kit/scrapy/__init__.py
spider_brew_kit/scrapy/middlewares/__init__.py
spider_brew_kit/scrapy/middlewares/proxy_connection_close.py
spider_brew_kit/scrapy/pipelines/__init__.py
spider_brew_kit/scrapy/pipelines/crawl_one_pipeline.py
spider_brew_kit/scrapy/pipelines/mongo_pipeline.py
spider_brew_kit/scrapy/playwright/__init__.py
spider_brew_kit/scrapy/playwright/request.py
spider_brew_kit/tools/__init__.py
spider_brew_kit/tools/text_encode.py
spider_brew_kit-0.1.6.dist-info/LICENSE
spider_brew_kit-0.1.6.dist-info/METADATA
spider_brew_kit-0.1.6.dist-info/WHEEL
spider_brew_kit-0.1.6.dist-info/RECORD
