Metadata-Version: 2.1
Name: spider-brew-kit
Version: 0.1.6
Summary: 
Home-page: https://spider-brew-kit.readthedocs.io/en/latest/
License: Apache-2.0
Keywords: spider,scrapy,spider-tool-kit,spider-kit,spider-tools,spider-tool-kit
Author: Pony.Ma
Author-email: mtf201013@gmail.com
Requires-Python: >=3.10,<4.0
Classifier: License :: OSI Approved :: Apache Software License
Classifier: Programming Language :: Python :: 3
Classifier: Programming Language :: Python :: 3.10
Classifier: Programming Language :: Python :: 3.11
Classifier: Programming Language :: Python :: 3.12
Requires-Dist: redis (>=4.6.0)
Requires-Dist: scrapy (>=2.7.0,<3.0.0)
Requires-Dist: scrapy-playwright (>=0.0.26,<0.0.27)
Project-URL: Documentation, https://spider-brew-kit.readthedocs.io/en/latest/
Project-URL: Repository, https://github.com/ma-pony/spider-tool-kit
